active_com
